{"cameraMode":{"drawMode":0,"name":"Shaded","section":"Shading Mode"},"sceneLighting":false,"audioPlay":false,"sceneViewState":{"m_AlwaysRefresh":false,"showFog":true,"showSkybox":false,"showFlares":true,"showImageEffects":true,"showParticleSystems":true,"showVisualEffectGraphs":true,"m_FxEnabled":true},"in2DMode":false,"pivot":{"x":0.3852691650390625,"y":2.6444625854492189,"z":-3.433880567550659},"rotation":{"x":0.23289138078689576,"y":0.0772167444229126,"z":-0.018540777266025544,"w":0.9692450761795044},"size":5.250448703765869,"orthographic":false}